# 🔄 Source Code vs Bytecode vs Binary Code

---

## 📊 COMPARISON TABLE

### Quick Overview

```
┌─────────────────┬────────────────────┬────────────────────┬──────────────────┐
│     ASPECT      │   SOURCE CODE      │    BYTECODE        │   BINARY CODE    │
├─────────────────┼────────────────────┼────────────────────┼──────────────────┤
│ Format          │ Human-readable     │ Intermediate       │ Machine-readable │
│ Example         │ .java, .py, .js    │ .class, .pyc       │ .exe, .bin, .o   │
│ Created By      │ Developer writes   │ Compiler generates │ Assembler/JIT    │
│ Readability     │ ✅ Very Easy       │ ⚠️ Medium          │ ❌ Very Hard     │
│ Executes?       │ No - needs compile │ Via VM/Interpreter │ Yes - Direct CPU │
│ Platform        │ Independent        │ Independent (VM)   │ Dependent (CPU)  │
│ Security        │ 🔴 Exposed         │ 🟡 Protected       │ 🟢 Obfuscated    │
└─────────────────┴────────────────────┴────────────────────┴──────────────────┘
```

---

## 🎯 DETAILED COMPARISON TABLE

| **Criteria** | **Source Code** | **Bytecode** | **Binary Code** |
|:---|:---|:---|:---|
| **Definition** | Text written by programmers in high-level language | Intermediate representation after compilation | Native machine instructions for CPU |
| **Written By** | Humans (Developers) | Compilers/Interpreters | JIT Compilers / Assemblers |
| **File Type** | `.java`, `.py`, `.js`, `.cpp`, `.c` | `.class`, `.pyc`, `.wasm` | `.exe`, `.bin`, `.o`, `.so` |
| **Example** | `print("Hello")` | `LOAD_CONST` `CALL_FUNCTION` | `55 48 89 e5 c3` |
| **Can Read?** | ✅ YES - Anyone | ⚠️ SOMETIMES - With tools | ❌ NO - Only CPU |
| **Can Reverse?** | ✅ Everyone sees it | ⚠️ Can decompile | ❌ Very difficult |
| **Performance** | Slowest (need compile) | Medium (interpreted) | Fastest ⚡ |
| **Platform Independent?** | YES (same code runs everywhere) | YES (VM runs everywhere) | NO (CPU-specific) |
| **File Size** | Larger | Medium | Smallest |
| **Security Level** | 🔴 LOW | 🟡 MEDIUM | 🟢 HIGH |

---

## 💻 REAL EXAMPLE: Step-by-Step

### **STEP 1️⃣ : SOURCE CODE** (What Programmer Writes)

**File:** `Calculator.java`

```java
public class Calculator {
    public static int add(int a, int b) {
        return a + b;
    }

    public static void main(String[] args) {
        int result = add(5, 3);
        System.out.println("Result: " + result);
    }
}
```

**Characteristics:**
- ✅ Easy to read and understand
- ✅ Contains comments & formatting
- ✅ Shows clear logic flow
- ❌ Cannot be executed directly by CPU

---

### **STEP 2️⃣ : BYTECODE** (After Compilation)

**File:** `Calculator.class` (JVM Bytecode)

**Command to compile:**
```bash
javac Calculator.java
```

**Bytecode representation:**
```
add(int, int):
  0: iload_0           // Load 1st integer parameter
  1: iload_1           // Load 2nd integer parameter
  2: iadd              // Add them (i = integer)
  3: ireturn           // Return result

main(String[]):
  0: bipush        5   // Push 5 onto stack
  2: bipush        3   // Push 3 onto stack
  4: invokestatic  #2  // Call add(5, 3)
  7: istore_1          // Store result
  8: getstatic     #3  // Get System.out
 11: ldc           #6  // Load "Result: "
 13: invokevirtual #7  // Append string
 16: iload_1           // Load result
 17: invokevirtual #8  // Append number
 20: invokevirtual #9  // Convert to String
 23: invokevirtual #10 // Print to console
 26: return
```

**Characteristics:**
- ⚠️ Semi-readable (needs knowledge)
- ⚠️ Uses stack-based operations
- ⚠️ References to methods (#2, #3, etc.)
- ✅ Platform independent (runs on any JVM)
- ❌ Still cannot run on CPU directly

---

### **STEP 3️⃣ : BINARY CODE** (Native Machine Instructions)

**File:** `Calculator.exe` or JVM running bytecode

**Binary representation (x86-64 assembly):**
```nasm
add function:
  55                    ; push rbp
  48 89 e5              ; mov rbp, rsp
  89 7d fc              ; mov [rbp-4], edi    (save 1st param)
  89 75 f8              ; mov [rbp-8], esi    (save 2nd param)
  8b 45 fc              ; mov eax, [rbp-4]    (load 1st param)
  03 45 f8              ; add eax, [rbp-8]    (add 2nd param)
  5d                    ; pop rbp
  c3                    ; ret                 (return)

main function:
  55                    ; push rbp
  b8 05 00 00 00        ; mov eax, 5          (5 in register)
  b9 03 00 00 00        ; mov ecx, 3          (3 in register)
  01 c8                 ; add eax, ecx        (5 + 3)
  c3                    ; ret
```

**Hex dump (what's in the executable):**
```
55 48 89 e5 89 7d fc 89 75 f8 8b 45 fc 03 45 f8 5d c3
```

**Characteristics:**
- ❌ NOT human-readable
- ❌ CPU-specific (x86-64 shown above)
- ✅ Executes directly & instantly
- ✅ Most secure (hard to reverse engineer)
- ✅ Only format CPU understands

---

## 🔄 EXECUTION FLOW DIAGRAM

```
┌──────────────────────────────────────────────────────────────────────┐
│                  CODE TRANSFORMATION PIPELINE                        │
└──────────────────────────────────────────────────────────────────────┘

   Developer creates              Compiler translates           CPU executes
          ↓                               ↓                           ↓
    ┌──────────────┐            ┌─────────────────┐        ┌───────────────┐
    │ SOURCE CODE  │  ──JAVAC──> │   BYTECODE      │──JIT──>│ BINARY CODE   │
    │ (Human)      │            │ (Intermediate)  │        │ (Machine)     │
    │ .java file   │            │ .class file     │        │ CPU instrs.   │
    └──────────────┘            └─────────────────┘        └───────────────┘
         ⏱️ Edit time              ⏱️ Compile time             ⏱️ Runtime
         (Developer)              (Once)                    (Every execution)
```

---

## 🚀 EXAMPLE WITH PYTHON

### **Source Code** (Human writes this)
```python
def add(a, b):
    return a + b

result = add(5, 3)
print(f"Result: {result}")
```

### **Bytecode** (Python compiler creates this)
```
  2           0 LOAD_CONST               1 (<code>)
              2 MAKE_FUNCTION            0
              4 STORE_NAME               0 (add)

  5           6 LOAD_NAME                0 (add)
              8 LOAD_CONST               2 (5)
             10 LOAD_CONST               3 (3)
             12 CALL_FUNCTION            2
             14 STORE_NAME               1 (result)

  6          16 LOAD_NAME                2 (print)
             18 LOAD_CONST               4 ('Result: {0}')
             20 FORMAT_VALUE             0
             22 CALL_FUNCTION            1
             24 POP_TOP
             26 LOAD_CONST               0 (None)
             28 RETURN_VALUE
```

### **Binary Code** (CPU executes this)
```
Machine code compiled from bytecode (when running with PyPy or CPython)
[Only CPU understands this representation]
```

---

## 📈 COMPARISON CHART

```
                    Readability
                        ↑
                        │
              Source Code │
                   ◆      │
                  / \     │  ✅ Humans prefer
                 /   \    │
            Bytecode  \   │
               ◆───────\──│
                \       \ │
             Binary ────◆─┴──→ Machine prefers ✅
                        
         Readability   Performance   Portability
         Source: 🟢    Source: 🔴    Source: 🟢
         Bytecode: 🟡  Bytecode: 🟡  Bytecode: 🟢
         Binary: 🔴    Binary: 🟢    Binary: 🔴
```

---

## 🎓 KEY TAKEAWAYS TABLE

| **When to Care?** | **What to Know** |
|---|---|
| **During Development** | Work with SOURCE CODE - readable & easy to debug |
| **After Compilation** | Use BYTECODE - portable across platforms & secure from casual viewing |
| **At Runtime** | System converts BYTECODE → BINARY CODE for CPU execution |
| **For Performance** | BINARY CODE runs fastest on specific hardware |
| **For Security** | BINARY CODE is hardest to reverse engineer |
| **For Portability** | SOURCE CODE & BYTECODE work everywhere with right tools |

---

## 📋 TL;DR - THE ESSENTIALS

### **What's the difference?**

```
🔵 SOURCE CODE     = Human-friendly instructions (readable)
🟠 BYTECODE        = Intermediate format (semi-readable, portable)
🔴 BINARY CODE     = CPU-friendly instructions (not readable, fast)
```

### **The Pipeline:**
```
Developer writes → Compiler → Bytecode → JIT/Interpreter → Binary → CPU
SOURCE CODE         JAVAC      (file)       (runtime)      (memory)   ⚡
```

### **Quick Comparison:**
- **Readable?** Source > Bytecode > Binary
- **Fast?** Binary > Bytecode > Source
- **Portable?** Source ≈ Bytecode >> Binary
- **Secure?** Binary > Bytecode > Source

### **Real World:**
- Java: `.java` (source) → `.class` (bytecode) → CPU instructions (binary)
- Python: `.py` (source) → `.pyc` (bytecode) → CPU instructions (binary)
- C++: `.cpp` (source) → `.exe` (binary directly)

---

## 🔗 RELATED TERMS

| Term | Meaning |
|---|---|
| **JVM** | Java Virtual Machine - reads bytecode and converts to binary |
| **JIT Compilation** | Just-In-Time - converts bytecode to binary at runtime |
| **Decompilation** | Converting bytecode/binary back to source code |
| **Assembly Language** | Human-readable version of binary code |
| **Machine Code** | The actual binary instructions |
| **Interpreter** | Reads source/bytecode line-by-line and executes |
| **Compiler** | Translates entire source to bytecode/binary at once |

---

**Last Updated:** 2026-07-14
